pwforecast.py
pwforecast-1.3.1.dist-info/LICENSE
pwforecast-1.3.1.dist-info/METADATA
pwforecast-1.3.1.dist-info/WHEEL
pwforecast-1.3.1.dist-info/top_level.txt
pwforecast-1.3.1.dist-info/RECORD
