Metadata-Version: 2.1
Name: pwforecast
Version: 1.3.1
Summary: A Python module to charge/discharge Tesla Powerwall based on solar forecast and peak/off peak tariffs.
Home-page: https://github.com/timhawker/pwforecast
Author: Tim Hawker
License: MIT
License-File: LICENSE
Requires-Dist: tzlocal
Requires-Dist: requests
Requires-Dist: python-dateutil
Requires-Dist: TeslaPy
